[
  {
    "id": "small-shipper",
    "name": "Small Shipper",
    "description": "Single-item and small orders",
    "dimensions": {
      "length": 6.1024,
      "width": 6.1024,
      "height": 2.5591
    },
    "dimensions_cm": {
      "length": 15.5,
      "width": 15.5,
      "height": 6.5
    },
    "unit": "in",
    "dimension_type": "inner",
    "inner_volume_cu_in": 95.30,
    "inventory_sku": "PO25000136",
    "aliases": ["Particle One Unit Shipper Box", "One Unit Shipper"],
    "source": "Logistics team — inside specs (cm converted to in)"
  },
  {
    "id": "large-shipper",
    "name": "Large Shipper",
    "description": "Multi-item and larger orders",
    "dimensions": {
      "length": 8.6614,
      "width": 6.8898,
      "height": 3.3465
    },
    "dimensions_cm": {
      "length": 22.0,
      "width": 17.5,
      "height": 8.5
    },
    "unit": "in",
    "dimension_type": "inner",
    "inner_volume_cu_in": 199.70,
    "inventory_sku": null,
    "aliases": [],
    "source": "Logistics team — inside specs (cm converted to in)"
  }
]
